globbing/__init__.py
globbing/handlers.py
globbing/version.py
jupyter_server_globbing-0.1.6.data/data/etc/jupyter/jupyter_server_config.d/globbing.json
jupyter_server_globbing-0.1.6.dist-info/METADATA
jupyter_server_globbing-0.1.6.dist-info/WHEEL
jupyter_server_globbing-0.1.6.dist-info/top_level.txt
jupyter_server_globbing-0.1.6.dist-info/RECORD
